setup.py
odette_probabiity.egg-info/PKG-INFO
odette_probabiity.egg-info/SOURCES.txt
odette_probabiity.egg-info/dependency_links.txt
odette_probabiity.egg-info/not-zip-safe
odette_probabiity.egg-info/top_level.txt
odette_probability/Binomialdistribution.py
odette_probability/Gaussiandistribution.py
odette_probability/Generaldistribution.py
odette_probability/__init__.py